LICENSE
MANIFEST.in
README.rst
setup.py
linefeeder/__init__.py
linefeeder.egg-info/PKG-INFO
linefeeder.egg-info/SOURCES.txt
linefeeder.egg-info/dependency_links.txt
linefeeder.egg-info/top_level.txt