Metadata-Version: 1.0
Name: linefeeder
Version: 0.0.3
Summary: feed bytes and get lines
Home-page: https://github.com/tomotaka/linefeeder
Author: Tomotaka Ito
Author-email: tomotaka.ito@gmail.com
License: The MIT License (MIT)
